typed_flags/__init__.py
typed_flags/typed_flags.py
discord_typed_flags-1.1.4.dist-info/METADATA
discord_typed_flags-1.1.4.dist-info/WHEEL
discord_typed_flags-1.1.4.dist-info/top_level.txt
discord_typed_flags-1.1.4.dist-info/RECORD
