Metadata-Version: 2.1
Name: discord-typed-flags
Version: 1.1.4
Summary: A Typehint based flags system for discord.py
Home-page: https://github.com/MenuDocs/Typed-Flags
Author: Menudocs
Author-email: contact@menudocs.org
License: UNKNOWN
Platform: UNKNOWN
Classifier: Programming Language :: Python :: 3
Classifier: License :: OSI Approved :: MIT License
Classifier: Operating System :: OS Independent
Classifier: Development Status :: 5 - Production/Stable
Requires-Python: >=3.8
Requires-Dist: discord.py (>=1)
